eidolon_savegame_editor
