Metadata-Version: 1.1
Name: eidolon-savegame-editor
Version: 0.2.2
Summary: Simple editor for the savegame file format used by Eidolon from Icewatergames.
Home-page: https://github.com/coddingtonbear/eidolon-savegame-editor
Author: Adam Coddington
Author-email: me@adamcoddington.net
License: UNKNOWN
Platform: UNKNOWN
Classifier: License :: OSI Approved :: MIT License
Classifier: Operating System :: OS Independent
Classifier: Programming Language :: Python :: 3
